asyncPyGithub/Repository.py
asyncPyGithub/User.py
asyncPyGithub/__init__.py
asyncPyGithub/base.py
asyncPyGithub/_types/__init__.py
asyncPyGithub/_types/base.py
asyncPyGithub/_types/content.py
asyncPyGithub/_types/repos.py
asyncPyGithub/_types/users.py
asyncpygithub-0.1.0.3.dist-info/METADATA
asyncpygithub-0.1.0.3.dist-info/WHEEL
asyncpygithub-0.1.0.3.dist-info/licenses/LICENSE
asyncpygithub-0.1.0.3.dist-info/RECORD
