Metadata-Version: 2.4
Name: asyncPyGithub
Version: 0.1.0.3
Summary: Async Python wrapper for the GitHub API
Project-URL: Homepage, https://github.com/sudoDeVinci/asyncPyGithub
Project-URL: Repository, https://github.com/sudoDeVinci/asyncPyGithub
Project-URL: Issues, https://github.com/sudoDeVinci/asyncPyGithub/issues
Author: sudoDeVinci
License-Expression: MIT
License-File: LICENSE
Keywords: api,async,asyncio,github,httpx
Classifier: Development Status :: 3 - Alpha
Classifier: Framework :: AsyncIO
Classifier: Intended Audience :: Developers
Classifier: License :: OSI Approved :: MIT License
Classifier: Operating System :: OS Independent
Classifier: Programming Language :: Python :: 3
Classifier: Programming Language :: Python :: 3.11
Classifier: Programming Language :: Python :: 3.12
Classifier: Programming Language :: Python :: 3.13
Classifier: Typing :: Typed
Requires-Python: >=3.11
Requires-Dist: email-validator>=2.0.0
Requires-Dist: httpx>=0.28.0
Requires-Dist: pydantic>=2.0.0
Requires-Dist: python-dotenv>=1.0.0
Provides-Extra: dev
Requires-Dist: black>=24.0.0; extra == 'dev'
Requires-Dist: mypy>=1.10.0; extra == 'dev'
Requires-Dist: pytest-asyncio>=1.0.0; extra == 'dev'
Requires-Dist: pytest>=8.0.0; extra == 'dev'
Requires-Dist: respx>=0.22.0; extra == 'dev'
